[
    {
        "advancement_cost": null,
        "agenda_points": null,
        "base_link": null,
        "code": "06025",
        "cost": 2,
        "deck_limit": 3,
        "faction_code": "jinteki",
        "faction_cost": 2,
        "id": "cerebral-static",
        "influence_limit": null,
        "keywords": "Current",
        "memory_cost": null,
        "minimum_deck_size": null,
        "side_code": "corp",
        "strength": null,
        "text": "This card is not trashed until another <strong>current</strong> is played or an agenda is stolen.\nThe Runner's identity text box is blank.",
        "title": "Cerebral Static",
        "trash_cost": null,
        "type_code": "operation",
        "uniqueness": false
    }
]
