[
    {
        "advancement_cost": 5,
        "agenda_points": 3,
        "base_link": null,
        "code": "13044",
        "cost": null,
        "deck_limit": 3,
        "faction_code": "weyland-consortium",
        "faction_cost": null,
        "id": "graft",
        "influence_limit": null,
        "keywords": null,
        "memory_cost": null,
        "minimum_deck_size": null,
        "side_code": "corp",
        "strength": null,
        "text": "When you score Graft, you may search your deck for up to 3 cards, reveal them, and add them to HQ. Shuffle R&D.",
        "title": "Graft",
        "trash_cost": null,
        "type_code": "agenda",
        "uniqueness": false
    }
]
