{
    "card_type_id": "hardware",
    "cost": 3,
    "deck_limit": 3,
    "faction_id": "neutral-runner",
    "id": "bmi-buffer",
    "influence_cost": 0,
    "side_id": "runner",
    "stripped_text": "Whenever a program is trashed from your grip, host it on BMI Buffer instead of adding it to your heap. click click: Install 1 hosted program (paying all costs).",
    "stripped_title": "BMI Buffer",
    "text": "Whenever a program is trashed from your grip, host it on BMI Buffer instead of adding it to your heap.\n[click][click]: Install 1 hosted program (paying all costs).",
    "title": "BMI Buffer",
    "uniqueness": false
}
