{
    "card_type_id": "operation",
    "cost": 2,
    "deck_limit": 3,
    "faction_id": "haas-bioroid",
    "id": "friends-in-high-places",
    "influence_cost": 1,
    "side_id": "corp",
    "stripped_text": "After you resolve this operation, end your action phase. Install up to 2 cards from Archives (paying all install costs).",
    "stripped_title": "Friends in High Places",
    "subtypes": [
        "terminal"
    ],
    "text": "After you resolve this operation, end your action phase.\nInstall up to 2 cards from Archives (paying all install costs).",
    "title": "Friends in High Places",
    "uniqueness": false
}
