{
    "card_type_id": "identity",
    "deck_limit": 1,
    "faction_id": "weyland-consortium",
    "id": "skorpios_defense_systems_persuasive_power",
    "influence_limit": 15,
    "is_unique": false,
    "minimum_deck_size": 40,
    "side_id": "corp",
    "stripped_text": "Interrupt -> Whenever 1 or more Runner cards would be trashed (from any location), set those cards aside instead of adding them to the heap. You can look at those cards. You may remove 1 of them from the game. Then, add all of those cards that are still set aside to the heap. Ignore this ability if you have already removed a card from the game with it this turn. Errata from CR 1.4",
    "stripped_title": "Skorpios Defense Systems: Persuasive Power",
    "subtypes": [
        "subsidiary"
    ],
    "text": "[interrupt] → Whenever 1 or more Runner cards would be trashed <em>(from any location)</em>, set those cards aside instead of adding them to the heap. You can look at those cards. You may remove 1 of them from the game. Then, add all of those cards that are still set aside to the heap. Ignore this ability if you have already removed a card from the game with it this turn.\n<errata>Errata from CR 1.4</errata>",
    "title": "Skorpios Defense Systems: Persuasive Power"
}
