[
    {
        "card_id": "disrupter",
        "card_set_id": "asis",
        "code": "02061",
        "flavor": "\"Saved my bacon more than once, but gives a wicked sense of déjà vu.\" -Whizzard",
        "illustrator": "Adam S. Doyle",
        "position": 61,
        "printed_text": "[interrupt] → [trash]: Reduce the base trace strength of a trace to 0.\n<errata>Errata from CR 1.4</errata>",
        "printed_uniqueness": false,
        "quantity": 3,
        "stripped_printed_text": "Interrupt -> trash: Reduce the base trace strength of a trace to 0. Errata from CR 1.4"
    },
    {
        "card_id": "force-of-nature",
        "card_set_id": "asis",
        "code": "02062",
        "flavor": "It always strikes twice.",
        "illustrator": "Ed Mattinian",
        "position": 62,
        "printed_text": "Interface → <strong>2[credit]:</strong> Break up to 2 <strong>code gate</strong> subroutines.\n<strong>1[credit]:</strong> +1 strength.",
        "printed_uniqueness": false,
        "quantity": 3,
        "stripped_printed_text": "Interface -> 2 credits: Break up to 2 code gate subroutines. 1 credit: +1 strength."
    },
    {
        "card_id": "scrubber",
        "card_set_id": "asis",
        "code": "02063",
        "flavor": "\"They're mindless tools of destruction, good for little else. Nice guys, though. Some of my best friends are scrubbers.\" -Ji \"Noise\" Reilly",
        "illustrator": "Mike Nesbitt",
        "position": 63,
        "printed_text": "2[recurring-credit] <em>(When you install this card and before your turn begins, refill to 2 hosted credits.)</em>\nYou can spend hosted credits to pay trash costs.",
        "printed_uniqueness": false,
        "quantity": 3,
        "stripped_printed_text": "2 recurring credits (When you install this card and before your turn begins, refill to 2 hosted credits.) You can spend hosted credits to pay trash costs."
    },
    {
        "card_id": "doppelganger",
        "card_set_id": "asis",
        "code": "02064",
        "flavor": "Twice the fun.",
        "illustrator": "Howard Schechlman",
        "position": 64,
        "printed_text": "+1[mu]\nOnce per turn, you may immediately make another run when a successful run ends.\nLimit 1 <strong>console</strong> per player.",
        "printed_uniqueness": true,
        "quantity": 3,
        "stripped_printed_text": "+1 mu Once per turn, you may immediately make another run when a successful run ends. Limit 1 console per player."
    },
    {
        "card_id": "crescentus",
        "card_set_id": "asis",
        "code": "02065",
        "flavor": "Cyberspace's strongest glue.",
        "illustrator": "Adam S. Doyle",
        "position": 65,
        "printed_text": "<strong>[trash]:</strong> Derez 1 piece of ice you fully broke during this encounter.",
        "printed_uniqueness": false,
        "quantity": 3,
        "stripped_printed_text": "trash: Derez 1 piece of ice you fully broke during this encounter."
    },
    {
        "card_id": "deus-x",
        "card_set_id": "asis",
        "code": "02066",
        "flavor": "Didn't see that coming.",
        "illustrator": "Andrew Mar",
        "position": 66,
        "printed_text": "Interface → <strong>[trash]:</strong> Break any number of <strong>AP</strong> subroutines.\n[interrupt] → <strong>[trash]:</strong> Prevent any amount of net damage.",
        "printed_uniqueness": false,
        "quantity": 3,
        "stripped_printed_text": "Interface -> trash: Break any number of AP subroutines. Interrupt -> trash: Prevent any amount of net damage."
    },
    {
        "card_id": "all-nighter",
        "card_set_id": "asis",
        "code": "02067",
        "flavor": "\"I don't care what the studies show. From my experience, I can ingest three cans of Diesel an hour for up to twelve hours before going into cardiac arrest.\" -heard during the eleventh hour",
        "illustrator": "Outland Entertainment LLC",
        "position": 67,
        "printed_text": "[click], [trash]: Gain [click][click].",
        "printed_uniqueness": false,
        "quantity": 3,
        "stripped_printed_text": "click, trash: Gain click click."
    },
    {
        "card_id": "inside-man",
        "card_set_id": "asis",
        "code": "02068",
        "flavor": "Few corporate employees have such wide-sweeping security clearance as the janitorial staff. Most corps foolishly think they're too dim-witted to take advantage of it.",
        "illustrator": "Mauricio Herrera",
        "position": 68,
        "printed_text": "2[recurring-credit]\nUse these credits to install hardware.",
        "printed_uniqueness": false,
        "quantity": 3,
        "stripped_printed_text": "2 recurring credits Use these credits to install hardware."
    },
    {
        "card_id": "underworld-contact",
        "card_set_id": "asis",
        "code": "02069",
        "flavor": "\"My boss rewards quality work. If you know what's good for you, you'll keep it up.\"",
        "illustrator": "Nate Stefan",
        "position": 69,
        "printed_text": "When your turn begins, gain 1[credit] if you have at least 2[link].",
        "printed_uniqueness": false,
        "quantity": 3,
        "stripped_printed_text": "When your turn begins, gain 1 credit if you have at least 2 link."
    },
    {
        "card_id": "green-level-clearance",
        "card_set_id": "asis",
        "code": "02070",
        "flavor": "Green-two clearance is the highest level of security a corp can gain access to. Legally, anyway.",
        "illustrator": "Mauricio Herrera",
        "position": 70,
        "printed_text": "Gain 3[credit] and draw 1 card.",
        "printed_uniqueness": false,
        "quantity": 3,
        "stripped_printed_text": "Gain 3 credits and draw 1 card."
    },
    {
        "card_id": "hourglass",
        "card_set_id": "asis",
        "code": "02071",
        "flavor": "Time just slips away.",
        "illustrator": "JuanManuel Tumburus",
        "position": 71,
        "printed_text": "[subroutine] The Runner loses [click], if able.\n[subroutine] The Runner loses [click], if able.\n[subroutine] The Runner loses [click], if able.",
        "printed_uniqueness": false,
        "quantity": 3,
        "stripped_printed_text": "Subroutine The Runner loses click, if able. Subroutine The Runner loses click, if able. Subroutine The Runner loses click, if able."
    },
    {
        "card_id": "dedicated-server",
        "card_set_id": "asis",
        "code": "02072",
        "flavor": "so very still, even\ncherry blossoms are not stirred\nby the temple bell\n-Fuhaku",
        "illustrator": "Emilio Rodriguez",
        "position": 72,
        "printed_text": "2[recurring-credit]\nUse these credits to rez ice.",
        "printed_uniqueness": false,
        "quantity": 3,
        "stripped_printed_text": "2 recurring credits Use these credits to rez ice."
    },
    {
        "card_id": "bullfrog",
        "card_set_id": "asis",
        "code": "02073",
        "illustrator": "Christina Davis",
        "position": 73,
        "printed_text": "[subroutine] You and the Runner secretly spend 0[credit], 1[credit] or 2[credit]. Reveal spent credits. If you and the Runner spent a different number of credits, move Bullfrog so that it is the outermost piece of ice protecting another server (the Runner continues the run from this new position and is now running on this new server).",
        "printed_uniqueness": false,
        "quantity": 3,
        "stripped_printed_text": "Subroutine You and the Runner secretly spend 0 credits, 1 credit or 2 credits. Reveal spent credits. If you and the Runner spent a different number of credits, move Bullfrog so that it is the outermost piece of ice protecting another server (the Runner continues the run from this new position and is now running on this new server)."
    },
    {
        "card_id": "uroboros",
        "card_set_id": "asis",
        "code": "02074",
        "flavor": "Where one thing ends, another begins.",
        "illustrator": "Liiga Smilshkalne",
        "position": 74,
        "printed_text": "[subroutine] <trace>Trace 4</trace> If successful, the Runner cannot make another run this turn.\n[subroutine] <trace>Trace 4</trace> If successful, end the run.",
        "printed_uniqueness": false,
        "quantity": 3,
        "stripped_printed_text": "Subroutine Trace 4 If successful, the Runner cannot make another run this turn. Subroutine Trace 4 If successful, end the run."
    },
    {
        "card_id": "net-police",
        "card_set_id": "asis",
        "code": "02075",
        "flavor": "This is the net. We work here. We're cops.",
        "illustrator": "Amelie Hutt",
        "position": 75,
        "printed_text": "X[recurring-credit]\nUse these credits during traces. X is the number of links the Runner has.",
        "printed_uniqueness": false,
        "quantity": 3,
        "stripped_printed_text": "X recurring credits Use these credits during traces. X is the number of links the Runner has."
    },
    {
        "card_id": "weyland-consortium-because-we-built-it",
        "card_set_id": "asis",
        "code": "02076",
        "flavor": "Constructing Cyberspace.",
        "position": 76,
        "printed_text": "1[recurring-credit]\nUse this credit to advance ice.",
        "printed_uniqueness": false,
        "quantity": 3,
        "stripped_printed_text": "1 recurring credit Use this credit to advance ice."
    },
    {
        "card_id": "government-contracts",
        "card_set_id": "asis",
        "code": "02077",
        "flavor": "It's really hard to lose a government contract.",
        "illustrator": "Mitchell Malloy",
        "position": 77,
        "printed_text": "[click], [click]: Gain 4[credit].",
        "printed_uniqueness": false,
        "quantity": 3,
        "stripped_printed_text": "click, click: Gain 4 credits."
    },
    {
        "card_id": "tyrant",
        "card_set_id": "asis",
        "code": "02078",
        "flavor": "Thou shall not pass.",
        "illustrator": "Isuardi Therianto",
        "position": 78,
        "printed_text": "Tyrant can be advanced only while rezzed and gains \"[subroutine] End the run.\" for each advancement token on it.",
        "printed_uniqueness": false,
        "quantity": 3,
        "stripped_printed_text": "Tyrant can be advanced only while rezzed and gains \"Subroutine End the run.\" for each advancement token on it."
    },
    {
        "card_id": "oversight-ai",
        "card_set_id": "asis",
        "code": "02079",
        "illustrator": "Mark Anthony Taduran",
        "position": 79,
        "printed_text": "Rez a piece of ice, ignoring all costs, and install Oversight AI on that ice as a hosted condition counter with the text \"Trash host ice if all its subroutines are broken during a single encounter.\"",
        "printed_uniqueness": false,
        "quantity": 3,
        "stripped_printed_text": "Rez a piece of ice, ignoring all costs, and install Oversight AI on that ice as a hosted condition counter with the text \"Trash host ice if all its subroutines are broken during a single encounter.\""
    },
    {
        "card_id": "false-lead",
        "card_set_id": "asis",
        "code": "02080",
        "flavor": "It didn't look like the headquarters of a multi-billion cred company. Probably because it wasn't.",
        "illustrator": "Bruno Balixa",
        "position": 80,
        "printed_text": "<strong>Forfeit this agenda:</strong> If the Runner has 2 or more [click] remaining, they lose [click][click].",
        "printed_uniqueness": false,
        "quantity": 3,
        "stripped_printed_text": "Forfeit this agenda: If the Runner has 2 or more click remaining, they lose click click."
    }
]
