[
    {
        "advancement_cost": null,
        "agenda_points": null,
        "base_link": null,
        "code": "12022",
        "cost": 3,
        "deck_limit": 3,
        "faction_code": "anarch",
        "faction_cost": 4,
        "id": "clan-vengeance",
        "influence_limit": null,
        "keywords": "Clan",
        "memory_cost": null,
        "minimum_deck_size": null,
        "side_code": "runner",
        "strength": null,
        "text": "Whenever you suffer any amount of damage, place 1 power counter on Clan Vengeance.\n[trash]: Trash 1 card from HQ at random for each power counter on Clan Vengeance.",
        "title": "Clan Vengeance",
        "trash_cost": null,
        "type_code": "resource",
        "uniqueness": false
    }
]
