[
    {
        "base_link": 0,
        "code": "30001",
        "faction_code": "anarch",
        "influence_limit": 15,
        "keywords": "G-mod",
        "minimum_deck_size": 40,
        "pack_code": "sg",
        "position": 1,
        "quantity": 1,
        "side_code": "runner",
        "text": "The first time each turn you trash a card you are accessing, you may draw 1 card and gain 1[c].",
        "title": "Jean \"Loup\" Arcemont: Party Animal",
        "type_code": "identity",
        "uniqueness": false
    },
    {
        "base_link": 0,
        "code": "30019",
        "faction_code": "shaper",
        "influence_limit": 15,
        "minimum_deck_size": 40,
        "pack_code": "sg",
        "position": 19,
        "quantity": 1,
        "side_code": "runner",
        "text": "Whenever an agenda is scored or stolen, you may swap 2 installed pieces of ice.",
        "title": "Tao Salonga: Telepresence Magician",
        "type_code": "identity",
        "uniqueness": false
    },
    {
        "code": "30023",
        "cost": 2,
        "deck_limit": 3,
        "faction_code": "shaper",
        "faction_cost": 3,
        "keywords": "Console",
        "pack_code": "sg",
        "position": 23,
        "quantity": 3,
        "side_code": "runner",
        "text": "+1[mu]\nWhenever an agenda is scored or stolen, you may gain 1[c]. Then, you may install 1 card.\nLimit 1 console per player.",
        "title": "Pantograph",
        "type_code": "hardware",
        "uniqueness": true
    },
    {
        "code": "30028",
        "cost": 0,
        "deck_limit": 3,
        "faction_code": "neutral-runner",
        "faction_cost": 0,
        "keywords": "Run",
        "pack_code": "sg",
        "position": 28,
        "quantity": 3,
        "side_code": "runner",
        "text": "Run HQ or R&D. If successful, draw 1 card and access 1 additional card from that server.",
        "title": "Jailbreak",
        "type_code": "event",
        "uniqueness": false
    },
    {
        "code": "30043",
        "faction_code": "jinteki",
        "influence_limit": 15,
        "minimum_deck_size": 40,
        "pack_code": "sg",
        "position": 43,
        "quantity": 1,
        "side_code": "corp",
        "text": "When your turn ends (after discarding cards down to maximum hand size), you may gain 1[credit] if there are 1 or more facedown cards in Archives.",
        "title": "Jinteki: Restoring Humanity",
        "type_code": "identity",
        "uniqueness": false
    },
    {
        "code": "30059",
        "faction_code": "weyland-consortium",
        "influence_limit": 15,
        "minimum_deck_size": 40,
        "pack_code": "sg",
        "position": 59,
        "quantity": 1,
        "side_code": "corp",
        "text": "Whenever you advance a card that does not have hosted advancement tokens, you may gain 2[credit].",
        "title": "Weyland Consortium: Built to Last",
        "type_code": "identity",
        "uniqueness": false
    }
]
