{
  "advancement_requirement": 4,
  "agenda_points": 2,
  "card_type_id": "agenda",
  "deck_limit": 3,
  "designed_by": "null_signal_games",
  "faction_id": "neutral_corp",
  "id": "cyberdex_sandbox",
  "influence_cost": 0,
  "is_unique": false,
  "side_id": "corp",
  "stripped_text": "The first time each turn you purge virus counters, gain 4 credits. When you score this agenda, you may purge virus counters.",
  "stripped_title": "Cyberdex Sandbox",
  "subtypes": ["security"],
  "text": "The first time each turn you purge virus counters, gain 4[credit].\nWhen you score this agenda, you may purge virus counters.",
  "title": "Cyberdex Sandbox"
}
