{
  "card_type_id": "operation",
  "cost": 2,
  "deck_limit": 3,
  "designed_by": "fantasy_flight_games",
  "faction_id": "nbn",
  "id": "invasion_of_privacy",
  "influence_cost": 3,
  "is_unique": false,
  "side_id": "corp",
  "stripped_text": "As an additional cost to play this operation, spend click. Trace[2]. If successful, reveal the grip. Trash up to X resources and/or events revealed this way, where X is equal to the amount by which your trace strength exceeded the Runner's link strength. If unsuccessful, take 1 bad publicity.",
  "stripped_title": "Invasion of Privacy",
  "subtypes": ["double", "gray_ops"],
  "text": "As an additional cost to play this operation, spend [click].\nTrace[2]. If successful, reveal the grip. Trash up to X resources and/or events revealed this way, where X is equal to the amount by which your trace strength exceeded the Runner's link strength. If unsuccessful, take 1 bad publicity.",
  "title": "Invasion of Privacy"
}
