{
  "card_type_id": "resource",
  "cost": 1,
  "deck_limit": 3,
  "faction_id": "neutral_runner",
  "id": "the_masque_b",
  "influence_cost": 0,
  "is_unique": true,
  "side_id": "runner",
  "stripped_text": "click,trash: Make a run and gain click. If that run is successful when it ends, you may immediately make another run on another server.",
  "stripped_title": "The Masque B",
  "subtypes": ["connection"],
  "text": "[click],[trash]: Make a run and gain [click]. If that run is successful when it ends, you may immediately make another run on another server.",
  "title": "The Masque B"
}
