{
  "card_type_id": "operation",
  "cost": 1,
  "deck_limit": 3,
  "designed_by": "fantasy_flight_games",
  "faction_id": "weyland_consortium",
  "id": "wake_up_call",
  "influence_cost": 3,
  "is_unique": false,
  "side_id": "corp",
  "stripped_text": "Play only if the Runner trashed a Corp card during their last turn and the Runner has at least 1 installed piece of hardware or non-virtual resource. The Runner must either trash that card or suffer 4 meat damage. Remove this operation from the game.",
  "stripped_title": "Wake Up Call",
  "subtypes": ["reprisal", "gray_ops"],
  "text": "Play only if the Runner trashed a Corp card during their last turn and the Runner has at least 1 installed piece of hardware or non-<strong>virtual</strong> resource.\nChoose 1 installed piece of hardware or non-<strong>virtual</strong> resource. The Runner must either trash that card or suffer 4 meat damage.\nRemove this operation from the game.",
  "title": "Wake Up Call"
}
