{
  "card_type_id": "ice",
  "cost": 2,
  "deck_limit": 3,
  "faction_id": "haas_bioroid",
  "id": "zed_1_0",
  "influence_cost": 2,
  "is_unique": false,
  "side_id": "corp",
  "strength": 1,
  "stripped_text": "Lose click: Break 1 subroutine on this ice. Only the Runner can use this ability. Subroutine If the Runner has lost click to break a subroutine during this run, do 1 core damage. Subroutine If the Runner has lost click to break a subroutine during this run, do 1 core damage.",
  "stripped_title": "Zed 1.0",
  "subtypes": ["sentry", "bioroid", "ap"],
  "text": "<strong>Lose [click]:</strong> Break 1 subroutine on this ice. Only the Runner can use this ability.\n[subroutine] If the Runner has lost [click] to break a subroutine during this run, do 1 core damage.\n[subroutine] If the Runner has lost [click] to break a subroutine during this run, do 1 core damage.",
  "title": "Zed 1.0"
}
