[
  {
    "answer": "No. Paige Piper interrupts the resolution of Frantic Coding, and as a search effect it shuffles the stack. After this, the cards that were looked at can no longer be confirmed and referenced, so the rest of Frantic Coding’s ability fails to resolve.",
    "card_id": "frantic_coding",
    "date_update": "2017-04-14",
    "nsg_rules_team_verified": false,
    "question": "####UFAQ [Michael Boggs]\nIf the Runner uses [Paige Piper](/en/card/08002) to find and trash the other copies of the card installed by Frantic Coding, are the rest of the cards looked at still trashed?"
  }
]
